4/computer organization/odev3/21011702.v
module RiscV_SingleCycle(
    input clk,
    input reset,
    output reg [31:0] pc,
    output reg [31:0] alu_result,
    output [31:0] write_data,
    input [31:0] read_data
);

    // Define memory
    reg [31:0] memory[0:1023]; // 1K words of memory
    reg [31:0] instruction_memory[0:255]; // 256 words of instruction memory

    // Register and next PC logic
    reg [31:0] next_pc;
    reg [31:0] registers[0:31];

    // Decode fields from instruction
    wire [31:0] instruction = instruction_memory[pc >> 2]; // Fetch instruction based on PC
    wire [6:0] opcode = instruction[6:0];
    wire [4:0] rd = instruction[11:7];
    wire [4:0] rs1 = instruction[19:15];
    wire [4:0] rs2 = instruction[24:20];
    wire [2:0] funct3 = instruction[14:12];
    wire [6:0] funct7 = instruction[31:25];
    wire [31:0] rs1_data = registers[rs1];
    wire [31:0] rs2_data = registers[rs2];

    // Immediate value processing
    wire signed [31:0] imm_i = {{20{instruction[31]}}, instruction[31:20]};
    wire signed [31:0] imm_s = {{20{instruction[31]}}, instruction[31:25], instruction[11:7]};
    wire signed [31:0] imm_b = {{19{instruction[31]}}, instruction[31], instruction[7], instruction[30:25], instruction[11:8], 1'b0};
    wire signed [31:0] sign_extended_imm = (opcode == 7'b0000011 || opcode == 7'b0010011) ? imm_i : imm_s;

    always @(posedge clk or posedge reset) begin
        if (reset) begin
            pc <= 0;
        end else begin
            pc <= next_pc;
        end
    end

    // ALU operation
    reg [31:0] alu_out;
    always @(*) begin
        case (opcode)
            7'b0110011: // R-type operations
                case (funct3)
                    3'b000: alu_out = (funct7 == 7'b0000000) ? rs1_data + rs2_data : rs1_data - rs2_data;
                    3'b101: alu_out = (funct7 == 7'b0100000) ? $signed(rs1_data) >>> rs2_data[4:0] : rs1_data >> rs2_data[4:0]; // Shift operations
                    3'b110: alu_out = rs1_data | rs2_data;
                    3'b111: alu_out = rs1_data & rs2_data;
                    3'b010: alu_out = ($signed(rs1_data) < $signed(rs2_data)) ? 1 : 0;
                endcase
            7'b0010011: // I-type ALU operations
                case (funct3)
                    3'b000: alu_out = rs1_data + sign_extended_imm; // addi
                    3'b110: alu_out = rs1_data | sign_extended_imm;
                    3'b111: alu_out = rs1_data & sign_extended_imm;
                    3'b010: alu_out = ($signed(rs1_data) < $signed(sign_extended_imm)) ? 1 : 0;
                endcase
            7'b0000011: // LW
                alu_out = rs1_data + sign_extended_imm;
            7'b0100011: // SW
                alu_out = rs1_data + sign_extended_imm;
            7'b1101111: // JAL
                alu_out = pc + {{12{instruction[31]}}, instruction[19:12], instruction[20], instruction[30:21], 1'b0};
            7'b1100011: // BEQ and other branches
                case (funct3)
                    3'b000: // beq
                        if (rs1_data == rs2_data) begin
                            alu_out = pc + imm_b;
                        end else begin
                            alu_out = pc + 4;
                        end
                    default: alu_out = pc + 4;
                endcase
            default: alu_out = pc + 4; // Default case for other instructions
        endcase
    end

    // Update alu_result on clock edge to capture the computed ALU output
    always @(posedge clk) begin
        alu_result <= alu_out;
    end

    // Write data to registers and handle load/store
    assign write_data = registers[rd];
    always @(posedge clk) begin
        if (!reset && rd != 0) begin
            if (opcode == 7'b0000011) // LW
                registers[rd] <= memory[alu_out[9:0]]; // Read from memory
            else if (opcode == 7'b0010011) // I-type instructions
                registers[rd] <= alu_out;
            else if (opcode == 7'b0110011) // R-type instructions
                registers[rd] <= alu_out;
        end
        if (opcode == 7'b0100011) // SW
            memory[alu_out[9:0]] <= rs2_data; // Write to memory
    end

    // Update next_pc
    always @(*) begin
        case (opcode)
            7'b1101111: // JAL
                next_pc = alu_out;
            7'b1100011: // BEQ and other branches
                if ((funct3 == 3'b000 && rs1_data == rs2_data) || 
                    (funct3 == 3'b001 && rs1_data != rs2_data)) begin
                    next_pc = pc + {{20{instruction[31]}}, instruction[7], instruction[30:25], instruction[11:8], 1'b0};
                end else begin
                    next_pc = pc + 4;
                end
            default:
                next_pc = pc + 4; // Default case for other instructions
        endcase
    end

    always @(posedge clk) begin
        $display("Time: %t, PC: %d, Next PC: %d, Opcode: %b, Funct3: %b, RS1 Data: %d, RS2 Data: %d, ALU Result: %d",
                 $time, pc, next_pc, opcode, funct3, rs1_data, rs2_data, alu_result);
        if (opcode == 7'b0100011) begin
            $display("SW: memory[%d] <= %d", alu_out[9:0], rs2_data);
        end
    end


    integer i;
    initial begin
        // Initialize ARR array
        memory[0] = 3; memory[1] = 7; memory[2] = 2; memory[3] = 6;
        memory[4] = 5; memory[5] = 4; memory[6] = 1; memory[7] = 1000;
        memory[8] = 999; memory[9] = 25; memory[10] = 90; memory[11] = 100;
        memory[12] = 30; memory[13] = 20; memory[14] = 10; memory[15] = 200;
        memory[16] = 3300; memory[17] = 250; memory[18] = 12; memory[19] = 75;

        // Initialize COUNT array
        memory[20] = 17; memory[21] = 13; memory[22] = 18; memory[23] = 14;
        memory[24] = 15; memory[25] = 16; memory[26] = 19; memory[27] = 1;
        memory[28] = 2; memory[29] = 9; memory[30] = 6; memory[31] = 5;
        memory[32] = 8; memory[33] = 10; memory[34] = 12; memory[35] = 4;
        memory[36] = 0; memory[37] = 3; memory[38] = 11; memory[39] = 7;

        // Reset RESULT array
        for (i = 40; i < 60; i = i + 1) begin
            memory[i] = 0;
        end
    end

endmodule

4/computer organization/odev3/21011702_tb.v
`timescale 1ns / 1ps
`include "single.v"

module TestBench;
    reg clk = 0;
    reg reset = 1;

    wire [31:0] pc;
    wire [31:0] alu_result;
    wire [31:0] write_data;
    wire [31:0] read_data = 32'b0;

    RiscV_SingleCycle uut(
        .clk(clk),
        .reset(reset),
        .pc(pc),
        .alu_result(alu_result),
        .write_data(write_data),
        .read_data(read_data)
    );

    always #10 clk = !clk;

    initial begin
        $dumpfile("processor_sim.vcd");
        $dumpvars(0, TestBench);

        // Assert reset
        reset = 1;
        #20; // Hold reset for 20ns
        reset = 0;

        // Initialize registers
        uut.registers[0] = 0;  // R0 = 0
        uut.instruction_memory[0] = 32'h00000093; // addi x1, zero, 0
        uut.instruction_memory[1] = 32'h01400113; // addi x2, zero, 20
        uut.instruction_memory[2] = 32'h02800193; // addi x3, zero, 40
        uut.instruction_memory[3] = 32'h01400213; // addi x4, zero, 20
        //loop:
        uut.instruction_memory[4] = 32'h02020263; // beq x4, x4, 8
        uut.instruction_memory[5] = 32'h0000a283; // lw x5, 0(x1)
        uut.instruction_memory[6] = 32'h00012303; // lw x6, 0(x2)
        uut.instruction_memory[7] = 32'h003303b3; // add x7, x6, x3
        uut.instruction_memory[8] = 32'h0053a023; // sw x5, 0(x7)
        uut.instruction_memory[9] = 32'h00108093; // addi x1, zero, 1
        uut.instruction_memory[10] = 32'h00110113; // addi x2, zero, 1
        uut.instruction_memory[11] = 32'hfff20213; // addi x4, x4, -1
        uut.instruction_memory[12] = 32'hfe1ff06f; // jal x0, -32
        //end:
        uut.instruction_memory[13] = 32'h00a00893; // addi x17, zero, 10
        uut.instruction_memory[14] = 32'h00000073; // ecall

        #4800;
        for (integer i = 40; i < 60; i++) begin
            $display("Memory[%d]: %d", i, uut.memory[i]);
        end
        $finish;
    end
endmodule

4/computer organization/odev3/21011702.vcd
$date
	Sun May 19 23:06:36 2024
$end
$version
	Icarus Verilog
$end
$timescale
	1ps
$end
$scope module TestBench $end
$var wire 32 ! read_data [31:0] $end
$var wire 32 " write_data [31:0] $end
$var wire 32 # pc [31:0] $end
$var wire 32 $ alu_result [31:0] $end
$var reg 1 % clk $end
$var reg 1 & reset $end
$scope module uut $end
$var wire 1 % clk $end
$var wire 32 ' instruction [31:0] $end
$var wire 32 ( read_data [31:0] $end
$var wire 1 & reset $end
$var wire 32 ) rs1_data [31:0] $end
$var wire 32 * rs2_data [31:0] $end
$var wire 32 + write_data [31:0] $end
$var wire 32 , sign_extended_imm [31:0] $end
$var wire 5 - rs2 [4:0] $end
$var wire 5 . rs1 [4:0] $end
$var wire 5 / rd [4:0] $end
$var wire 7 0 opcode [6:0] $end
$var wire 32 1 imm_s [31:0] $end
$var wire 32 2 imm_i [31:0] $end
$var wire 32 3 imm_b [31:0] $end
$var wire 7 4 funct7 [6:0] $end
$var wire 3 5 funct3 [2:0] $end
$var reg 32 6 alu_out [31:0] $end
$var reg 32 7 alu_result [31:0] $end
$var reg 32 8 next_pc [31:0] $end
$var reg 32 9 pc [31:0] $end
$var integer 32 : i [31:0] $end
$upscope $end
$scope begin $ivl_for_loop0 $end
$var integer 32 ; i [31:0] $end
$upscope $end
$upscope $end
$enddefinitions $end
$comment Show the parameter values. $end
$dumpall
$end
#0
$dumpvars
bx ;
b111100 :
b0 9
b100 8
bx 7
b100 6
bx 5
bx 4
bx0 3
bx 2
bx 1
bx 0
bx /
bx .
bx -
bx ,
bx +
bx *
bx )
b0 (
bx '
1&
0%
bx $
b0 #
bx "
b0 !
$end
#10000
b100 $
b100 7
1%
#20000
b0 ,
b0 6
b10011 0
b1 /
b0 )
b0 .
b0 *
b0 -
b0 5
b0 4
b0 2
b1 1
b100000000000 3
0%
b10010011 '
0&
#30000
b10100 6
b10100 ,
b10 /
bx *
b10100 -
b10100 2
b10 1
b10 3
b1000 8
b1010000000000000100010011 '
bx "
bx +
b0 $
b0 7
b100 #
b100 9
1%
#40000
0%
#50000
b101000 6
b101000 ,
b11 /
b1000 -
b1 4
b101000 2
b100011 1
b100000100010 3
b1100 8
b10100000000000000110010011 '
b10100 $
b10100 7
bx "
bx +
b1000 #
b1000 9
1%
#60000
0%
#70000
b10100 6
b10100 ,
b100 /
b10100 -
b0 4
b10100 2
b100 1
b100 3
b10000 8
b1010000000000001000010011 '
bx "
bx +
b101000 $
b101000 7
b1100 #
b1100 9
1%
#80000
0%
#90000
b100100 ,
b1100011 0
b10100 )
b100 .
b0 *
b0 -
b1 4
b100000 2
b100100 1
b100100 3
b10100 8
b10000000100000001001100011 '
b10100 $
b10100 7
b10100 "
b10100 +
b10000 #
b10000 9
1%
#100000
0%
#110000
b0 ,
b11 0
bx "
bx +
b101 /
b0 )
b1 .
b10 5
b0 4
b0 2
b101 1
b100000000100 3
b11000 8
b0 6
b1010001010000011 '
b10100 #
b10100 9
1%
#120000
0%
#130000
b10100 6
b110 /
b10100 )
b10 .
b110 1
b110 3
b11100 8
b10010001100000011 '
b0 $
b0 7
bx "
bx +
b11000 #
b11000 9
1%
#140000
0%
#150000
b111 ,
b111001 6
b110011 0
b111 /
b10001 )
b110 .
b101000 *
b11 -
b0 5
b11 2
b111 1
b100000000110 3
b100000 8
b1100110000001110110011 '
bx "
bx +
b10100 $
b10100 7
b11100 #
b11100 9
1%
#160000
0%
#170000
b0 ,
b111001 6
b100011 0
b0 /
b111001 )
b111 .
b11 *
b101 -
b10 5
b101 2
b0 1
b0 3
b100100 8
b10100111010000000100011 '
b111001 $
b111001 7
b0 "
b0 +
b100000 #
b100000 9
1%
#180000
0%
#190000
b1 ,
b1 6
b10011 0
b1 /
b0 )
b1 .
b0 *
b1 -
b0 5
b1 2
b1 1
b100000000000 3
b101000 8
b100001000000010010011 '
b100100 #
b100100 9
1%
#200000
0%
#210000
b10 /
b10 .
b10 1
b10 3
b101100 8
b10101 6
b100010000000100010011 '
b1 $
b1 7
b10100 )
b1 *
b10100 "
b10100 +
b101000 #
b101000 9
1%
#220000
0%
#230000
b11111111111111111111111111111111 ,
b100 /
b100 .
bx *
b11111 -
b1111111 4
b11111111111111111111111111111111 2
b11111111111111111111111111100100 1
b11111111111111111111011111100100 3
b110000 8
b10011 6
b11111111111100100000001000010011 '
b10100 )
b10100 "
b10100 +
b10101 $
b10101 7
b101100 #
b101100 9
1%
#240000
0%
#250000
b11111111111111111111111111100000 ,
b1101111 0
b0 /
b11111 .
b1 *
b1 -
b111 5
b11111111111111111111111111100001 2
b11111111111111111111111111100000 1
b11111111111111111111011111100000 3
b10000 8
b10000 6
b11111110000111111111000001101111 '
b10011 $
b10011 7
bx )
b0 "
b0 +
b110000 #
b110000 9
1%
#260000
0%
#270000
b100100 ,
b1100011 0
b10011 "
b10011 +
b100 /
b10011 )
b100 .
b0 *
b0 -
b0 5
b1 4
b100000 2
b100100 1
b100100 3
b10100 8
b10100 6
b10000000100000001001100011 '
b10000 $
b10000 7
b10000 #
b10000 9
1%
#280000
0%
#290000
b0 ,
b11 0
b11 "
b11 +
b101 /
b1 )
b1 .
b10 5
b0 4
b0 2
b101 1
b100000000100 3
b11000 8
b1 6
b1010001010000011 '
b10100 $
b10100 7
b10100 #
b10100 9
1%
#300000
0%
#310000
b10101 6
b110 /
b10101 )
b10 .
b110 1
b110 3
b11100 8
b10010001100000011 '
b10001 "
b10001 +
b1 $
b1 7
b11000 #
b11000 9
1%
#320000
0%
#330000
b111 ,
b110101 6
b110011 0
b111 /
b1101 )
b110 .
b101000 *
b11 -
b0 5
b11 2
b111 1
b100000000110 3
b100000 8
b1100110000001110110011 '
b10101 $
b10101 7
b111001 "
b111001 +
b11100 #
b11100 9
1%
#340000
0%
#350000
b0 ,
b110101 6
b100011 0
b0 /
b110101 )
b111 .
b111 *
b101 -
b10 5
b101 2
b0 1
b0 3
b100100 8
b10100111010000000100011 '
b0 "
b0 +
b110101 $
b110101 7
b100000 #
b100000 9
1%
#360000
0%
#370000
b1 ,
b10 6
b10011 0
b1 "
b1 +
b1 /
b1 )
b1 .
b1 *
b1 -
b0 5
b1 2
b1 1
b100000000000 3
b101000 8
b100001000000010010011 '
b100100 #
b100100 9
1%
#380000
0%
#390000
b10 /
b10 .
b10 1
b10 3
b101100 8
b10110 6
b100010000000100010011 '
b10101 )
b10 *
b10101 "
b10101 +
b10 $
b10 7
b101000 #
b101000 9
1%
#400000
0%
#410000
b11111111111111111111111111111111 ,
b100 /
b100 .
bx *
b11111 -
b1111111 4
b11111111111111111111111111111111 2
b11111111111111111111111111100100 1
b11111111111111111111011111100100 3
b110000 8
b10010 6
b11111111111100100000001000010011 '
b10110 $
b10110 7
b10011 )
b10011 "
b10011 +
b101100 #
b101100 9
1%
#420000
0%
#430000
b11111111111111111111111111100000 ,
b1101111 0
b0 /
b11111 .
b10 *
b1 -
b111 5
b11111111111111111111111111100001 2
b11111111111111111111111111100000 1
b11111111111111111111011111100000 3
b10000 8
b10000 6
b11111110000111111111000001101111 '
bx )
b0 "
b0 +
b10010 $
b10010 7
b110000 #
b110000 9
1%
#440000
0%
#450000
b100100 ,
b1100011 0
b10010 "
b10010 +
b100 /
b10010 )
b100 .
b0 *
b0 -
b0 5
b1 4
b100000 2
b100100 1
b100100 3
b10100 8
b10100 6
b10000000100000001001100011 '
b10000 $
b10000 7
b10000 #
b10000 9
1%
#460000
0%
#470000
b0 ,
b11 0
b111 "
b111 +
b101 /
b10 )
b1 .
b10 5
b0 4
b0 2
b101 1
b100000000100 3
b11000 8
b10 6
b1010001010000011 '
b10100 $
b10100 7
b10100 #
b10100 9
1%
#480000
0%
#490000
b10110 6
b110 /
b10110 )
b10 .
b110 1
b110 3
b11100 8
b10010001100000011 '
b10 $
b10 7
b1101 "
b1101 +
b11000 #
b11000 9
1%
#500000
0%
#510000
b111 ,
b111010 6
b110011 0
b111 /
b10010 )
b110 .
b101000 *
b11 -
b0 5
b11 2
b111 1
b100000000110 3
b100000 8
b1100110000001110110011 '
b110101 "
b110101 +
b10110 $
b10110 7
b11100 #
b11100 9
1%
#520000
0%
#530000
b0 ,
b111010 6
b100011 0
b0 /
b111010 )
b111 .
b10 *
b101 -
b10 5
b101 2
b0 1
b0 3
b100100 8
b10100111010000000100011 '
b111010 $
b111010 7
b0 "
b0 +
b100000 #
b100000 9
1%
#540000
0%
#550000
b1 ,
b11 6
b10011 0
b10 "
b10 +
b1 /
b10 )
b1 .
b1 -
b0 5
b1 2
b1 1
b100000000000 3
b101000 8
b100001000000010010011 '
b100100 #
b100100 9
1%
#560000
0%
#570000
b10 /
b10 .
b10 1
b10 3
b101100 8
b10111 6
b100010000000100010011 '
b11 $
b11 7
b10110 )
b11 *
b10110 "
b10110 +
b101000 #
b101000 9
1%
#580000
0%
#590000
b11111111111111111111111111111111 ,
b100 /
b100 .
bx *
b11111 -
b1111111 4
b11111111111111111111111111111111 2
b11111111111111111111111111100100 1
b11111111111111111111011111100100 3
b110000 8
b10001 6
b11111111111100100000001000010011 '
b10010 )
b10010 "
b10010 +
b10111 $
b10111 7
b101100 #
b101100 9
1%
#600000
0%
#610000
b11111111111111111111111111100000 ,
b1101111 0
b0 /
b11111 .
b11 *
b1 -
b111 5
b11111111111111111111111111100001 2
b11111111111111111111111111100000 1
b11111111111111111111011111100000 3
b10000 8
b10000 6
b11111110000111111111000001101111 '
b10001 $
b10001 7
bx )
b0 "
b0 +
b110000 #
b110000 9
1%
#620000
0%
#630000
b100100 ,
b1100011 0
b10001 "
b10001 +
b100 /
b10001 )
b100 .
b0 *
b0 -
b0 5
b1 4
b100000 2
b100100 1
b100100 3
b10100 8
b10100 6
b10000000100000001001100011 '
b10000 $
b10000 7
b10000 #
b10000 9
1%
#640000
0%
#650000
b0 ,
b11 0
b10 "
b10 +
b101 /
b11 )
b1 .
b10 5
b0 4
b0 2
b101 1
b100000000100 3
b11000 8
b11 6
b1010001010000011 '
b10100 $
b10100 7
b10100 #
b10100 9
1%
#660000
0%
#670000
b10111 6
b110 /
b10111 )
b10 .
b110 1
b110 3
b11100 8
b10010001100000011 '
b10010 "
b10010 +
b11 $
b11 7
b11000 #
b11000 9
1%
#680000
0%
#690000
b111 ,
b110110 6
b110011 0
b111 /
b1110 )
b110 .
b101000 *
b11 -
b0 5
b11 2
b111 1
b100000000110 3
b100000 8
b1100110000001110110011 '
b10111 $
b10111 7
b111010 "
b111010 +
b11100 #
b11100 9
1%
#700000
0%
#710000
b0 ,
b110110 6
b100011 0
b0 /
b110110 )
b111 .
b110 *
b101 -
b10 5
b101 2
b0 1
b0 3
b100100 8
b10100111010000000100011 '
b0 "
b0 +
b110110 $
b110110 7
b100000 #
b100000 9
1%
#720000
0%
#730000
b1 ,
b100 6
b10011 0
b11 "
b11 +
b1 /
b11 )
b1 .
b11 *
b1 -
b0 5
b1 2
b1 1
b100000000000 3
b101000 8
b100001000000010010011 '
b100100 #
b100100 9
1%
#740000
0%
#750000
b10 /
b10 .
b10 1
b10 3
b101100 8
b11000 6
b100010000000100010011 '
b10111 )
b100 *
b10111 "
b10111 +
b100 $
b100 7
b101000 #
b101000 9
1%
#760000
0%
#770000
b11111111111111111111111111111111 ,
b100 /
b100 .
bx *
b11111 -
b1111111 4
b11111111111111111111111111111111 2
b11111111111111111111111111100100 1
b11111111111111111111011111100100 3
b110000 8
b10000 6
b11111111111100100000001000010011 '
b11000 $
b11000 7
b10001 )
b10001 "
b10001 +
b101100 #
b101100 9
1%
#780000
0%
#790000
b11111111111111111111111111100000 ,
b1101111 0
b0 /
b11111 .
b100 *
b1 -
b111 5
b11111111111111111111111111100001 2
b11111111111111111111111111100000 1
b11111111111111111111011111100000 3
b10000 8
b10000 6
b11111110000111111111000001101111 '
bx )
b0 "
b0 +
b10000 $
b10000 7
b110000 #
b110000 9
1%
#800000
0%
#810000
b100100 ,
b1100011 0
b10000 "
b10000 +
b100 /
b10000 )
b100 .
b0 *
b0 -
b0 5
b1 4
b100000 2
b100100 1
b100100 3
b10100 8
b10100 6
b10000000100000001001100011 '
b10000 #
b10000 9
1%
#820000
0%
#830000
b0 ,
b11 0
b110 "
b110 +
b101 /
b100 )
b1 .
b10 5
b0 4
b0 2
b101 1
b100000000100 3
b11000 8
b100 6
b1010001010000011 '
b10100 $
b10100 7
b10100 #
b10100 9
1%
#840000
0%
#850000
b11000 6
b110 /
b11000 )
b10 .
b110 1
b110 3
b11100 8
b10010001100000011 '
b100 $
b100 7
b1110 "
b1110 +
b11000 #
b11000 9
1%
#860000
0%
#870000
b111 ,
b110111 6
b110011 0
b111 /
b1111 )
b110 .
b101000 *
b11 -
b0 5
b11 2
b111 1
b100000000110 3
b100000 8
b1100110000001110110011 '
b110110 "
b110110 +
b11000 $
b11000 7
b11100 #
b11100 9
1%
#880000
0%
#890000
b0 ,
b110111 6
b100011 0
b0 /
b110111 )
b111 .
b101 *
b101 -
b10 5
b101 2
b0 1
b0 3
b100100 8
b10100111010000000100011 '
b110111 $
b110111 7
b0 "
b0 +
b100000 #
b100000 9
1%
#900000
0%
#910000
b1 ,
b101 6
b10011 0
b100 "
b100 +
b1 /
b100 )
b1 .
b100 *
b1 -
b0 5
b1 2
b1 1
b100000000000 3
b101000 8
b100001000000010010011 '
b100100 #
b100100 9
1%
#920000
0%
#930000
b10 /
b10 .
b10 1
b10 3
b101100 8
b11001 6
b100010000000100010011 '
b101 $
b101 7
b11000 )
b101 *
b11000 "
b11000 +
b101000 #
b101000 9
1%
#940000
0%
#950000
b11111111111111111111111111111111 ,
b100 /
b100 .
bx *
b11111 -
b1111111 4
b11111111111111111111111111111111 2
b11111111111111111111111111100100 1
b11111111111111111111011111100100 3
b110000 8
b1111 6
b11111111111100100000001000010011 '
b10000 )
b10000 "
b10000 +
b11001 $
b11001 7
b101100 #
b101100 9
1%
#960000
0%
#970000
b11111111111111111111111111100000 ,
b1101111 0
b0 /
b11111 .
b101 *
b1 -
b111 5
b11111111111111111111111111100001 2
b11111111111111111111111111100000 1
b11111111111111111111011111100000 3
b10000 8
b10000 6
b11111110000111111111000001101111 '
b1111 $
b1111 7
bx )
b0 "
b0 +
b110000 #
b110000 9
1%
#980000
0%
#990000
b100100 ,
b1100011 0
b1111 "
b1111 +
b100 /
b1111 )
b100 .
b0 *
b0 -
b0 5
b1 4
b100000 2
b100100 1
b100100 3
b10100 8
b10100 6
b10000000100000001001100011 '
b10000 $
b10000 7
b10000 #
b10000 9
1%
#1000000
0%
#1010000
b0 ,
b11 0
b101 "
b101 +
b101 /
b101 )
b1 .
b10 5
b0 4
b0 2
b101 1
b100000000100 3
b11000 8
b101 6
b1010001010000011 '
b10100 $
b10100 7
b10100 #
b10100 9
1%
#1020000
0%
#1030000
b11001 6
b110 /
b11001 )
b10 .
b110 1
b110 3
b11100 8
b10010001100000011 '
b1111 "
b1111 +
b101 $
b101 7
b11000 #
b11000 9
1%
#1040000
0%
#1050000
b111 ,
b111000 6
b110011 0
b111 /
b10000 )
b110 .
b101000 *
b11 -
b0 5
b11 2
b111 1
b100000000110 3
b100000 8
b1100110000001110110011 '
b11001 $
b11001 7
b110111 "
b110111 +
b11100 #
b11100 9
1%
#1060000
0%
#1070000
b0 ,
b111000 6
b100011 0
b0 /
b111000 )
b111 .
b100 *
b101 -
b10 5
b101 2
b0 1
b0 3
b100100 8
b10100111010000000100011 '
b0 "
b0 +
b111000 $
b111000 7
b100000 #
b100000 9
1%
#1080000
0%
#1090000
b1 ,
b110 6
b10011 0
b101 "
b101 +
b1 /
b101 )
b1 .
b101 *
b1 -
b0 5
b1 2
b1 1
b100000000000 3
b101000 8
b100001000000010010011 '
b100100 #
b100100 9
1%
#1100000
0%
#1110000
b10 /
b10 .
b10 1
b10 3
b101100 8
b11010 6
b100010000000100010011 '
b11001 )
b110 *
b11001 "
b11001 +
b110 $
b110 7
b101000 #
b101000 9
1%
#1120000
0%
#1130000
b11111111111111111111111111111111 ,
b100 /
b100 .
bx *
b11111 -
b1111111 4
b11111111111111111111111111111111 2
b11111111111111111111111111100100 1
b11111111111111111111011111100100 3
b110000 8
b1110 6
b11111111111100100000001000010011 '
b11010 $
b11010 7
b1111 )
b1111 "
b1111 +
b101100 #
b101100 9
1%
#1140000
0%
#1150000
b11111111111111111111111111100000 ,
b1101111 0
b0 /
b11111 .
b110 *
b1 -
b111 5
b11111111111111111111111111100001 2
b11111111111111111111111111100000 1
b11111111111111111111011111100000 3
b10000 8
b10000 6
b11111110000111111111000001101111 '
bx )
b0 "
b0 +
b1110 $
b1110 7
b110000 #
b110000 9
1%
#1160000
0%
#1170000
b100100 ,
b1100011 0
b1110 "
b1110 +
b100 /
b1110 )
b100 .
b0 *
b0 -
b0 5
b1 4
b100000 2
b100100 1
b100100 3
b10100 8
b10100 6
b10000000100000001001100011 '
b10000 $
b10000 7
b10000 #
b10000 9
1%
#1180000
0%
#1190000
b0 ,
b11 0
b100 "
b100 +
b101 /
b110 )
b1 .
b10 5
b0 4
b0 2
b101 1
b100000000100 3
b11000 8
b110 6
b1010001010000011 '
b10100 $
b10100 7
b10100 #
b10100 9
1%
#1200000
0%
#1210000
b11010 6
b110 /
b11010 )
b10 .
b110 1
b110 3
b11100 8
b10010001100000011 '
b110 $
b110 7
b10000 "
b10000 +
b11000 #
b11000 9
1%
#1220000
0%
#1230000
b111 ,
b111011 6
b110011 0
b111 /
b10011 )
b110 .
b101000 *
b11 -
b0 5
b11 2
b111 1
b100000000110 3
b100000 8
b1100110000001110110011 '
b111000 "
b111000 +
b11010 $
b11010 7
b11100 #
b11100 9
1%
#1240000
0%
#1250000
b0 ,
b111011 6
b100011 0
b0 /
b111011 )
b111 .
b1 *
b101 -
b10 5
b101 2
b0 1
b0 3
b100100 8
b10100111010000000100011 '
b111011 $
b111011 7
b0 "
b0 +
b100000 #
b100000 9
1%
#1260000
0%
#1270000
b1 ,
b111 6
b10011 0
b110 "
b110 +
b1 /
b110 )
b1 .
b110 *
b1 -
b0 5
b1 2
b1 1
b100000000000 3
b101000 8
b100001000000010010011 '
b100100 #
b100100 9
1%
#1280000
0%
#1290000
b10 /
b10 .
b10 1
b10 3
b101100 8
b11011 6
b100010000000100010011 '
b111 $
b111 7
b11010 )
b111 *
b11010 "
b11010 +
b101000 #
b101000 9
1%
#1300000
0%
#1310000
b11111111111111111111111111111111 ,
b100 /
b100 .
bx *
b11111 -
b1111111 4
b11111111111111111111111111111111 2
b11111111111111111111111111100100 1
b11111111111111111111011111100100 3
b110000 8
b1101 6
b11111111111100100000001000010011 '
b1110 )
b1110 "
b1110 +
b11011 $
b11011 7
b101100 #
b101100 9
1%
#1320000
0%
#1330000
b11111111111111111111111111100000 ,
b1101111 0
b0 /
b11111 .
b111 *
b1 -
b111 5
b11111111111111111111111111100001 2
b11111111111111111111111111100000 1
b11111111111111111111011111100000 3
b10000 8
b10000 6
b11111110000111111111000001101111 '
b1101 $
b1101 7
bx )
b0 "
b0 +
b110000 #
b110000 9
1%
#1340000
0%
#1350000
b100100 ,
b1100011 0
b1101 "
b1101 +
b100 /
b1101 )
b100 .
b0 *
b0 -
b0 5
b1 4
b100000 2
b100100 1
b100100 3
b10100 8
b10100 6
b10000000100000001001100011 '
b10000 $
b10000 7
b10000 #
b10000 9
1%
#1360000
0%
#1370000
b0 ,
b11 0
b1 "
b1 +
b101 /
b111 )
b1 .
b10 5
b0 4
b0 2
b101 1
b100000000100 3
b11000 8
b111 6
b1010001010000011 '
b10100 $
b10100 7
b10100 #
b10100 9
1%
#1380000
0%
#1390000
b11011 6
b110 /
b11011 )
b10 .
b110 1
b110 3
b11100 8
b10010001100000011 '
b10011 "
b10011 +
b111 $
b111 7
b11000 #
b11000 9
1%
#1400000
0%
#1410000
b111 ,
b101001 6
b110011 0
b111 /
b1 )
b110 .
b101000 *
b11 -
b0 5
b11 2
b111 1
b100000000110 3
b100000 8
b1100110000001110110011 '
b11011 $
b11011 7
b111011 "
b111011 +
b11100 #
b11100 9
1%
#1420000
0%
#1430000
b0 ,
b101001 6
b100011 0
b0 /
b101001 )
b111 .
b1111101000 *
b101 -
b10 5
b101 2
b0 1
b0 3
b100100 8
b10100111010000000100011 '
b0 "
b0 +
b101001 $
b101001 7
b100000 #
b100000 9
1%
#1440000
0%
#1450000
b1 ,
b1000 6
b10011 0
b111 "
b111 +
b1 /
b111 )
b1 .
b111 *
b1 -
b0 5
b1 2
b1 1
b100000000000 3
b101000 8
b100001000000010010011 '
b100100 #
b100100 9
1%
#1460000
0%
#1470000
b10 /
b10 .
b10 1
b10 3
b101100 8
b11100 6
b100010000000100010011 '
b11011 )
b1000 *
b11011 "
b11011 +
b1000 $
b1000 7
b101000 #
b101000 9
1%
#1480000
0%
#1490000
b11111111111111111111111111111111 ,
b100 /
b100 .
bx *
b11111 -
b1111111 4
b11111111111111111111111111111111 2
b11111111111111111111111111100100 1
b11111111111111111111011111100100 3
b110000 8
b1100 6
b11111111111100100000001000010011 '
b11100 $
b11100 7
b1101 )
b1101 "
b1101 +
b101100 #
b101100 9
1%
#1500000
0%
#1510000
b11111111111111111111111111100000 ,
b1101111 0
b0 /
b11111 .
b1000 *
b1 -
b111 5
b11111111111111111111111111100001 2
b11111111111111111111111111100000 1
b11111111111111111111011111100000 3
b10000 8
b10000 6
b11111110000111111111000001101111 '
bx )
b0 "
b0 +
b1100 $
b1100 7
b110000 #
b110000 9
1%
#1520000
0%
#1530000
b100100 ,
b1100011 0
b1100 "
b1100 +
b100 /
b1100 )
b100 .
b0 *
b0 -
b0 5
b1 4
b100000 2
b100100 1
b100100 3
b10100 8
b10100 6
b10000000100000001001100011 '
b10000 $
b10000 7
b10000 #
b10000 9
1%
#1540000
0%
#1550000
b0 ,
b11 0
b1111101000 "
b1111101000 +
b101 /
b1000 )
b1 .
b10 5
b0 4
b0 2
b101 1
b100000000100 3
b11000 8
b1000 6
b1010001010000011 '
b10100 $
b10100 7
b10100 #
b10100 9
1%
#1560000
0%
#1570000
b11100 6
b110 /
b11100 )
b10 .
b110 1
b110 3
b11100 8
b10010001100000011 '
b1000 $
b1000 7
b1 "
b1 +
b11000 #
b11000 9
1%
#1580000
0%
#1590000
b111 ,
b101010 6
b110011 0
b111 /
b10 )
b110 .
b101000 *
b11 -
b0 5
b11 2
b111 1
b100000000110 3
b100000 8
b1100110000001110110011 '
b101001 "
b101001 +
b11100 $
b11100 7
b11100 #
b11100 9
1%
#1600000
0%
